aliyunsdkens/__init__.py
aliyunsdkens/request/__init__.py
aliyunsdkens/request/v20171110/AccosicateNetworkAclRequest.py
aliyunsdkens/request/v20171110/AddBackendServersRequest.py
aliyunsdkens/request/v20171110/AddNetworkInterfaceToInstanceRequest.py
aliyunsdkens/request/v20171110/AddSnatIpForSnatEntryRequest.py
aliyunsdkens/request/v20171110/AssignPrivateIpAddressesRequest.py
aliyunsdkens/request/v20171110/AssociateEnsEipAddressRequest.py
aliyunsdkens/request/v20171110/AssociateHaVipRequest.py
aliyunsdkens/request/v20171110/AttachDiskRequest.py
aliyunsdkens/request/v20171110/AttachEnsInstancesRequest.py
aliyunsdkens/request/v20171110/AttachInstanceSDGRequest.py
aliyunsdkens/request/v20171110/AttachNetworkInterfaceRequest.py
aliyunsdkens/request/v20171110/AuthorizeSecurityGroupEgressRequest.py
aliyunsdkens/request/v20171110/AuthorizeSecurityGroupRequest.py
aliyunsdkens/request/v20171110/CleanDistDataRequest.py
aliyunsdkens/request/v20171110/CopySDGRequest.py
aliyunsdkens/request/v20171110/CopySnapshotRequest.py
aliyunsdkens/request/v20171110/CreateARMServerInstancesRequest.py
aliyunsdkens/request/v20171110/CreateApplicationRequest.py
aliyunsdkens/request/v20171110/CreateClassicNetworkRequest.py
aliyunsdkens/request/v20171110/CreateClusterRequest.py
aliyunsdkens/request/v20171110/CreateDiskRequest.py
aliyunsdkens/request/v20171110/CreateEipInstanceRequest.py
aliyunsdkens/request/v20171110/CreateEnsRouteEntryRequest.py
aliyunsdkens/request/v20171110/CreateEnsSaleControlRequest.py
aliyunsdkens/request/v20171110/CreateEnsServiceRequest.py
aliyunsdkens/request/v20171110/CreateEpnInstanceRequest.py
aliyunsdkens/request/v20171110/CreateFileSystemRequest.py
aliyunsdkens/request/v20171110/CreateForwardEntryRequest.py
aliyunsdkens/request/v20171110/CreateHaVipRequest.py
aliyunsdkens/request/v20171110/CreateImageRequest.py
aliyunsdkens/request/v20171110/CreateInstanceActiveOpsTaskRequest.py
aliyunsdkens/request/v20171110/CreateInstanceRequest.py
aliyun_python_sdk_ens-3.0.23.dist-info/LICENSE
aliyun_python_sdk_ens-3.0.23.dist-info/METADATA
aliyun_python_sdk_ens-3.0.23.dist-info/WHEEL
aliyun_python_sdk_ens-3.0.23.dist-info/top_level.txt
aliyun_python_sdk_ens-3.0.23.dist-info/RECORD
